[
  {
    "id": "ai-xavier-init-case-1-a-too-large-initialization-leads-to-explodi-1",
    "articleSlug": "xavier-init",
    "articleTitle": "Xavier Initialization",
    "category": "Data/Training",
    "chapter": "The Problem of Exploding or Vanishing Gradients",
    "title": "Case 1: a Too-large Initialization Leads to Exploding Gradients",
    "order": 1,
    "orderInChapter": 1,
    "contentHtml": "<ul>\n  <li>Consider the case where every weight is initialized slightly larger than the identity matrix.</li>\n</ul>\n<div class=\"MathJax_Display\" style=\"text-align: center;\"><span class=\"MathJax\" id=\"MathJax-Element-20-Frame\" tabindex=\"0\" data-mathml=\"<math xmlns=&quot;http://www.w3.org/1998/Math/MathML&quot; display=&quot;block&quot;><msup><mi>W</mi><mrow class=&quot;MJX-TeXAtom-ORD&quot;><mo stretchy=&quot;false&quot;>[</mo><mn>1</mn><mo stretchy=&quot;false&quot;>]</mo></mrow></msup><mo>=</mo><msup><mi>W</mi><mrow class=&quot;MJX-TeXAtom-ORD&quot;><mo stretchy=&quot;false&quot;>[</mo><mn>2</mn><mo stretchy=&quot;false&quot;>]</mo></mrow></msup><mo>=</mo><mo>&amp;#x22EF;</mo><mo>=</mo><msup><mi>W</mi><mrow class=&quot;MJX-TeXAtom-ORD&quot;><mo stretchy=&quot;false&quot;>[</mo><mi>L</mi><mo>&amp;#x2212;</mo><mn>1</mn><mo stretchy=&quot;false&quot;>]</mo></mrow></msup><mo>=</mo><mrow><mo>[</mo><mtable rowspacing=&quot;4pt&quot; columnspacing=&quot;1em&quot;><mtr><mtd><mn>1.5</mn></mtd><mtd><mn>0</mn></mtd></mtr><mtr><mtd><mn>0</mn></mtd><mtd><mn>1.5</mn></mtd></mtr></mtable><mo>]</mo></mrow></math>\" role=\"presentation\" style=\"text-align: center; position: relative;\"><nobr aria-hidden=\"true\"><span class=\"math\" id=\"MathJax-Span-240\" style=\"width: 20.784em; display: inline-block;\"><span style=\"display: inline-block; position: relative; width: 17.294em; height: 0px; font-size: 120%;\"><span style=\"position: absolute; clip: rect(2.503em, 1017.09em, 5.263em, -999.997em); top: -4.112em; left: 0em;\"><span class=\"mrow\" id=\"MathJax-Span-241\"><span class=\"msubsup\" id=\"MathJax-Span-242\"><span style=\"display: inline-block; position: relative; width: 1.878em; height: 0px;\"><span style=\"position: absolute; clip: rect(3.18em, 1000.89em, 4.169em, -999.997em); top: -4.008em; left: 0em;\"><span class=\"mi\" id=\"MathJax-Span-243\" style=\"font-family: STIXGeneral-Italic;\">W<span style=\"display: inline-block; overflow: hidden; height: 1px; width: 0.055em;\"></span></span><span style=\"display: inline-block; width: 0px; height: 4.013em;\"></span></span><span style=\"position: absolute; top: -4.424em; left: 0.992em;\"><span class=\"texatom\" id=\"MathJax-Span-244\"><span class=\"mrow\" id=\"MathJax-Span-245\"><span class=\"mo\" id=\"MathJax-Span-246\" style=\"font-size: 70.7%; font-family: STIXGeneral-Regular;\">[</span><span class=\"mn\" id=\"MathJax-Span-247\" style=\"font-size: 70.7%; font-family: STIXGeneral-Regular;\">1</span><span class=\"mo\" id=\"MathJax-Span-248\" style=\"font-size: 70.7%; font-family: STIXGeneral-Regular;\">]</span></span></span><span style=\"display: inline-block; width: 0px; height: 4.013em;\"></span></span></span></span><span class=\"mo\" id=\"MathJax-Span-249\" style=\"font-family: STIXGeneral-Regular; padding-left: 0.315em;\">=</span><span class=\"msubsup\" id=\"MathJax-Span-250\" style=\"padding-left: 0.315em;\"><span style=\"display: inline-block; position: relative; width: 1.878em; height: 0px;\"><span style=\"position: absolute; clip: rect(3.18em, 1000.89em, 4.169em, -999.997em); top: -4.008em; left: 0em;\"><span class=\"mi\" id=\"MathJax-Span-251\" style=\"font-family: STIXGeneral-Italic;\">W<span style=\"display: inline-block; overflow: hidden; height: 1px; width: 0.055em;\"></span></span><span style=\"display: inline-block; width: 0px; height: 4.013em;\"></span></span><span style=\"position: absolute; top: -4.424em; left: 0.992em;\"><span class=\"texatom\" id=\"MathJax-Span-252\"><span class=\"mrow\" id=\"MathJax-Span-253\"><span class=\"mo\" id=\"MathJax-Span-254\" style=\"font-size: 70.7%; font-family: STIXGeneral-Regular;\">[</span><span class=\"mn\" id=\"MathJax-Span-255\" style=\"font-size: 70.7%; font-family: STIXGeneral-Regular;\">2</span><span class=\"mo\" id=\"MathJax-Span-256\" style=\"font-size: 70.7%; font-family: STIXGeneral-Regular;\">]</span></span></span><span style=\"display: inline-block; width: 0px; height: 4.013em;\"></span></span></span></span><span class=\"mo\" id=\"MathJax-Span-257\" style=\"font-family: STIXGeneral-Regular; padding-left: 0.315em;\">=</span><span class=\"mo\" id=\"MathJax-Span-258\" style=\"font-family: STIXGeneral-Regular; padding-left: 0.315em;\">⋯</span><span class=\"mo\" id=\"MathJax-Span-259\" style=\"font-family: STIXGeneral-Regular; padding-left: 0.315em;\">=</span><span class=\"msubsup\" id=\"MathJax-Span-260\" style=\"padding-left: 0.315em;\"><span style=\"display: inline-block; position: relative; width: 2.763em; height: 0px;\"><span style=\"position: absolute; clip: rect(3.18em, 1000.89em, 4.169em, -999.997em); top: -4.008em; left: 0em;\"><span class=\"mi\" id=\"MathJax-Span-261\" style=\"font-family: STIXGeneral-Italic;\">W<span style=\"display: inline-block; overflow: hidden; height: 1px; width: 0.055em;\"></span></span><span style=\"display: inline-block; width: 0px; height: 4.013em;\"></span></span><span style=\"position: absolute; top: -4.424em; left: 0.992em;\"><span class=\"texatom\" id=\"MathJax-Span-262\"><span class=\"mrow\" id=\"MathJax-Span-263\"><span class=\"mo\" id=\"MathJax-Span-264\" style=\"font-size: 70.7%; font-family: STIXGeneral-Regular;\">[</span><span class=\"mi\" id=\"MathJax-Span-265\" style=\"font-size: 70.7%; font-family: STIXGeneral-Italic;\">L<span style=\"display: inline-block; overflow: hidden; height: 1px; width: 0.003em;\"></span></span><span class=\"mo\" id=\"MathJax-Span-266\" style=\"font-size: 70.7%; font-family: STIXGeneral-Regular;\">−</span><span class=\"mn\" id=\"MathJax-Span-267\" style=\"font-size: 70.7%; font-family: STIXGeneral-Regular;\">1</span><span class=\"mo\" id=\"MathJax-Span-268\" style=\"font-size: 70.7%; font-family: STIXGeneral-Regular;\">]</span></span></span><span style=\"display: inline-block; width: 0px; height: 4.013em;\"></span></span></span></span><span class=\"mo\" id=\"MathJax-Span-269\" style=\"font-family: STIXGeneral-Regular; padding-left: 0.315em;\">=</span><span class=\"mrow\" id=\"MathJax-Span-270\" style=\"padding-left: 0.315em;\"><span class=\"mo\" id=\"MathJax-Span-271\" style=\"vertical-align: -0.57em;\"><span style=\"font-family: STIXSizeThreeSym;\">[</span></span><span class=\"mtable\" id=\"MathJax-Span-272\" style=\"padding-right: 0.159em; padding-left: 0.159em;\"><span style=\"display: inline-block; position: relative; width: 3.648em; height: 0px;\"><span style=\"position: absolute; clip: rect(2.503em, 1001.2em, 4.951em, -999.997em); top: -4.008em; left: 0em;\"><span style=\"display: inline-block; position: relative; width: 1.253em; height: 0px;\"><span style=\"position: absolute; clip: rect(3.18em, 1001.2em, 4.169em, -999.997em); top: -4.685em; left: 50%; margin-left: -0.622em;\"><span class=\"mtd\" id=\"MathJax-Span-273\"><span class=\"mrow\" id=\"MathJax-Span-274\"><span class=\"mn\" id=\"MathJax-Span-275\" style=\"font-family: STIXGeneral-Regular;\">1.5</span></span></span><span style=\"display: inline-block; width: 0px; height: 4.013em;\"></span></span><span style=\"position: absolute; clip: rect(3.18em, 1000.47em, 4.169em, -999.997em); top: -3.227em; left: 50%; margin-left: -0.258em;\"><span class=\"mtd\" id=\"MathJax-Span-279\"><span class=\"mrow\" id=\"MathJax-Span-280\"><span class=\"mn\" id=\"MathJax-Span-281\" style=\"font-family: STIXGeneral-Regular;\">0</span></span></span><span style=\"display: inline-block; width: 0px; height: 4.013em;\"></span></span></span><span style=\"display: inline-block; width: 0px; height: 4.013em;\"></span></span><span style=\"position: absolute; clip: rect(2.503em, 1001.2em, 4.951em, -999.997em); top: -4.008em; left: 2.398em;\"><span style=\"display: inline-block; position: relative; width: 1.253em; height: 0px;\"><span style=\"position: absolute; clip: rect(3.18em, 1000.47em, 4.169em, -999.997em); top: -4.685em; left: 50%; margin-left: -0.258em;\"><span class=\"mtd\" id=\"MathJax-Span-276\"><span class=\"mrow\" id=\"MathJax-Span-277\"><span class=\"mn\" id=\"MathJax-Span-278\" style=\"font-family: STIXGeneral-Regular;\">0</span></span></span><span style=\"display: inline-block; width: 0px; height: 4.013em;\"></span></span><span style=\"position: absolute; clip: rect(3.18em, 1001.2em, 4.169em, -999.997em); top: -3.227em; left: 50%; margin-left: -0.622em;\"><span class=\"mtd\" id=\"MathJax-Span-282\"><span class=\"mrow\" id=\"MathJax-Span-283\"><span class=\"mn\" id=\"MathJax-Span-284\" style=\"font-family: STIXGeneral-Regular;\">1.5</span></span></span><span style=\"display: inline-block; width: 0px; height: 4.013em;\"></span></span></span><span style=\"display: inline-block; width: 0px; height: 4.013em;\"></span></span></span></span><span class=\"mo\" id=\"MathJax-Span-285\" style=\"vertical-align: -0.57em;\"><span style=\"font-family: STIXSizeThreeSym;\">]</span></span></span></span><span style=\"display: inline-block; width: 0px; height: 4.117em;\"></span></span></span><span style=\"display: inline-block; overflow: hidden; vertical-align: -1.247em; border-left: 0px solid; width: 0px; height: 3.066em;\"></span></span></nobr><span class=\"MJX_Assistive_MathML MJX_Assistive_MathML_Block\" role=\"presentation\"><math xmlns=\"http://www.w3.org/1998/Math/MathML\" display=\"block\"><msup><mi>W</mi><mrow class=\"MJX-TeXAtom-ORD\"><mo stretchy=\"false\">[</mo><mn>1</mn><mo stretchy=\"false\">]</mo></mrow></msup><mo>=</mo><msup><mi>W</mi><mrow class=\"MJX-TeXAtom-ORD\"><mo stretchy=\"false\">[</mo><mn>2</mn><mo stretchy=\"false\">]</mo></mrow></msup><mo>=</mo><mo>⋯</mo><mo>=</mo><msup><mi>W</mi><mrow class=\"MJX-TeXAtom-ORD\"><mo stretchy=\"false\">[</mo><mi>L</mi><mo>−</mo><mn>1</mn><mo stretchy=\"false\">]</mo></mrow></msup><mo>=</mo><mrow><mo>[</mo><mtable rowspacing=\"4pt\" columnspacing=\"1em\"><mtr><mtd><mn>1.5</mn></mtd><mtd><mn>0</mn></mtd></mtr><mtr><mtd><mn>0</mn></mtd><mtd><mn>1.5</mn></mtd></mtr></mtable><mo>]</mo></mrow></math></span></span></div>\n<ul>\n  <li>This simplifies to <span class=\"MathJax_Preview\" style=\"color: inherit; display: none;\"></span><span class=\"MathJax\" id=\"MathJax-Element-21-Frame\" tabindex=\"0\" data-mathml=\"<math xmlns=&quot;http://www.w3.org/1998/Math/MathML&quot;><mrow class=&quot;MJX-TeXAtom-ORD&quot;><mover><mi>y</mi><mo stretchy=&quot;false&quot;>&amp;#x005E;</mo></mover></mrow><mo>=</mo><msup><mi>W</mi><mrow class=&quot;MJX-TeXAtom-ORD&quot;><mo stretchy=&quot;false&quot;>[</mo><mi>L</mi><mo stretchy=&quot;false&quot;>]</mo></mrow></msup><msup><mn>1.5</mn><mrow class=&quot;MJX-TeXAtom-ORD&quot;><mi>L</mi><mo>&amp;#x2212;</mo><mn>1</mn></mrow></msup><mi>x</mi></math>\" role=\"presentation\" style=\"position: relative;\"><nobr aria-hidden=\"true\"><span class=\"math\" id=\"MathJax-Span-286\" style=\"width: 8.023em; display: inline-block;\"><span style=\"display: inline-block; position: relative; width: 6.669em; height: 0px; font-size: 120%;\"><span style=\"position: absolute; clip: rect(1.148em, 1006.67em, 2.555em, -999.997em); top: -2.185em; left: 0em;\"><span class=\"mrow\" id=\"MathJax-Span-287\"><span class=\"texatom\" id=\"MathJax-Span-288\"><span class=\"mrow\" id=\"MathJax-Span-289\"><span class=\"munderover\" id=\"MathJax-Span-290\"><span style=\"display: inline-block; position: relative; width: 0.471em; height: 0px;\"><span style=\"position: absolute; clip: rect(3.44em, 1000.42em, 4.378em, -999.997em); top: -4.008em; left: 0em;\"><span class=\"mi\" id=\"MathJax-Span-291\" style=\"font-family: STIXGeneral-Italic;\">y</span><span style=\"display: inline-block; width: 0px; height: 4.013em;\"></span></span><span style=\"position: absolute; top: -4.06em; left: 0.055em;\"><span style=\"height: 0em; vertical-align: 0em; width: 0.367em; display: inline-block; overflow: hidden;\"></span><span class=\"mo\" id=\"MathJax-Span-292\" style=\"font-family: STIXGeneral-Regular;\">̂&nbsp;<span style=\"height: 0em; vertical-align: 0em; margin-left: -0.258em;\"></span></span><span style=\"display: inline-block; overflow: hidden; height: 1px; width: 0em;\"></span><span style=\"display: inline-block; width: 0px; height: 4.013em;\"></span></span></span></span></span></span><span class=\"mo\" id=\"MathJax-Span-293\" style=\"font-family: STIXGeneral-Regular; padding-left: 0.315em;\">=</span><span class=\"msubsup\" id=\"MathJax-Span-294\" style=\"padding-left: 0.315em;\"><span style=\"display: inline-block; position: relative; width: 1.93em; height: 0px;\"><span style=\"position: absolute; clip: rect(3.18em, 1000.89em, 4.169em, -999.997em); top: -4.008em; left: 0em;\"><span class=\"mi\" id=\"MathJax-Span-295\" style=\"font-family: STIXGeneral-Italic;\">W<span style=\"display: inline-block; overflow: hidden; height: 1px; width: 0.055em;\"></span></span><span style=\"display: inline-block; width: 0px; height: 4.013em;\"></span></span><span style=\"position: absolute; top: -4.372em; left: 0.992em;\"><span class=\"texatom\" id=\"MathJax-Span-296\"><span class=\"mrow\" id=\"MathJax-Span-297\"><span class=\"mo\" id=\"MathJax-Span-298\" style=\"font-size: 70.7%; font-family: STIXGeneral-Regular;\">[</span><span class=\"mi\" id=\"MathJax-Span-299\" style=\"font-size: 70.7%; font-family: STIXGeneral-Italic;\">L<span style=\"display: inline-block; overflow: hidden; height: 1px; width: 0.003em;\"></span></span><span class=\"mo\" id=\"MathJax-Span-300\" style=\"font-size: 70.7%; font-family: STIXGeneral-Regular;\">]</span></span></span><span style=\"display: inline-block; width: 0px; height: 4.013em;\"></span></span></span></span><span class=\"msubsup\" id=\"MathJax-Span-301\"><span style=\"display: inline-block; position: relative; width: 2.555em; height: 0px;\"><span style=\"position: absolute; clip: rect(3.18em, 1001.2em, 4.169em, -999.997em); top: -4.008em; left: 0em;\"><span class=\"mn\" id=\"MathJax-Span-302\" style=\"font-family: STIXGeneral-Regular;\">1.5</span><span style=\"display: inline-block; width: 0px; height: 4.013em;\"></span></span><span style=\"position: absolute; top: -4.424em; left: 1.253em;\"><span class=\"texatom\" id=\"MathJax-Span-303\"><span class=\"mrow\" id=\"MathJax-Span-304\"><span class=\"mi\" id=\"MathJax-Span-305\" style=\"font-size: 70.7%; font-family: STIXGeneral-Italic;\">L<span style=\"display: inline-block; overflow: hidden; height: 1px; width: 0.003em;\"></span></span><span class=\"mo\" id=\"MathJax-Span-306\" style=\"font-size: 70.7%; font-family: STIXGeneral-Regular;\">−</span><span class=\"mn\" id=\"MathJax-Span-307\" style=\"font-size: 70.7%; font-family: STIXGeneral-Regular;\">1</span></span></span><span style=\"display: inline-block; width: 0px; height: 4.013em;\"></span></span></span></span><span class=\"mi\" id=\"MathJax-Span-308\" style=\"font-family: STIXGeneral-Italic;\">x<span style=\"display: inline-block; overflow: hidden; height: 1px; width: 0.003em;\"></span></span></span><span style=\"display: inline-block; width: 0px; height: 2.19em;\"></span></span></span><span style=\"display: inline-block; overflow: hidden; vertical-align: -0.309em; border-left: 0px solid; width: 0px; height: 1.441em;\"></span></span></nobr><span class=\"MJX_Assistive_MathML\" role=\"presentation\"><math xmlns=\"http://www.w3.org/1998/Math/MathML\"><mrow class=\"MJX-TeXAtom-ORD\"><mover><mi>y</mi><mo stretchy=\"false\">^</mo></mover></mrow><mo>=</mo><msup><mi>W</mi><mrow class=\"MJX-TeXAtom-ORD\"><mo stretchy=\"false\">[</mo><mi>L</mi><mo stretchy=\"false\">]</mo></mrow></msup><msup><mn>1.5</mn><mrow class=\"MJX-TeXAtom-ORD\"><mi>L</mi><mo>−</mo><mn>1</mn></mrow></msup><mi>x</mi></math></span></span><script type=\"math/tex\" id=\"MathJax-Element-21\">\\hat{y} = W^{[L]}1.5^{L-1}x</script>, and the values of <span class=\"MathJax_Preview\" style=\"color: inherit; display: none;\"></span><span class=\"MathJax\" id=\"MathJax-Element-22-Frame\" tabindex=\"0\" data-mathml=\"<math xmlns=&quot;http://www.w3.org/1998/Math/MathML&quot;><msup><mi>a</mi><mrow class=&quot;MJX-TeXAtom-ORD&quot;><mo stretchy=&quot;false&quot;>[</mo><mi>l</mi><mo stretchy=&quot;false&quot;>]</mo></mrow></msup></math>\" role=\"presentation\" style=\"position: relative;\"><nobr aria-hidden=\"true\"><span class=\"math\" id=\"MathJax-Span-309\" style=\"width: 1.513em; display: inline-block;\"><span style=\"display: inline-block; position: relative; width: 1.253em; height: 0px; font-size: 120%;\"><span style=\"position: absolute; clip: rect(1.148em, 1001.25em, 2.294em, -999.997em); top: -2.133em; left: 0em;\"><span class=\"mrow\" id=\"MathJax-Span-310\"><span class=\"msubsup\" id=\"MathJax-Span-311\"><span style=\"display: inline-block; position: relative; width: 1.253em; height: 0px;\"><span style=\"position: absolute; clip: rect(3.44em, 1000.47em, 4.169em, -999.997em); top: -4.008em; left: 0em;\"><span class=\"mi\" id=\"MathJax-Span-312\" style=\"font-family: STIXGeneral-Italic;\">a</span><span style=\"display: inline-block; width: 0px; height: 4.013em;\"></span></span><span style=\"position: absolute; top: -4.372em; left: 0.523em;\"><span class=\"texatom\" id=\"MathJax-Span-313\"><span class=\"mrow\" id=\"MathJax-Span-314\"><span class=\"mo\" id=\"MathJax-Span-315\" style=\"font-size: 70.7%; font-family: STIXGeneral-Regular;\">[</span><span class=\"mi\" id=\"MathJax-Span-316\" style=\"font-size: 70.7%; font-family: STIXGeneral-Italic;\">l<span style=\"display: inline-block; overflow: hidden; height: 1px; width: 0.003em;\"></span></span><span class=\"mo\" id=\"MathJax-Span-317\" style=\"font-size: 70.7%; font-family: STIXGeneral-Regular;\">]</span></span></span><span style=\"display: inline-block; width: 0px; height: 4.013em;\"></span></span></span></span></span><span style=\"display: inline-block; width: 0px; height: 2.138em;\"></span></span></span><span style=\"display: inline-block; overflow: hidden; vertical-align: -0.059em; border-left: 0px solid; width: 0px; height: 1.128em;\"></span></span></nobr><span class=\"MJX_Assistive_MathML\" role=\"presentation\"><math xmlns=\"http://www.w3.org/1998/Math/MathML\"><msup><mi>a</mi><mrow class=\"MJX-TeXAtom-ORD\"><mo stretchy=\"false\">[</mo><mi>l</mi><mo stretchy=\"false\">]</mo></mrow></msup></math></span></span><script type=\"math/tex\" id=\"MathJax-Element-22\">a^{[l]}</script> increase exponentially with <span class=\"MathJax_Preview\" style=\"color: inherit; display: none;\"></span><span class=\"MathJax\" id=\"MathJax-Element-23-Frame\" tabindex=\"0\" data-mathml=\"<math xmlns=&quot;http://www.w3.org/1998/Math/MathML&quot;><mi>l</mi></math>\" role=\"presentation\" style=\"position: relative;\"><nobr aria-hidden=\"true\"><span class=\"math\" id=\"MathJax-Span-318\" style=\"width: 0.315em; display: inline-block;\"><span style=\"display: inline-block; position: relative; width: 0.263em; height: 0px; font-size: 120%;\"><span style=\"position: absolute; clip: rect(1.357em, 1000.26em, 2.346em, -999.997em); top: -2.185em; left: 0em;\"><span class=\"mrow\" id=\"MathJax-Span-319\"><span class=\"mi\" id=\"MathJax-Span-320\" style=\"font-family: STIXGeneral-Italic;\">l<span style=\"display: inline-block; overflow: hidden; height: 1px; width: 0.003em;\"></span></span></span><span style=\"display: inline-block; width: 0px; height: 2.19em;\"></span></span></span><span style=\"display: inline-block; overflow: hidden; vertical-align: -0.059em; border-left: 0px solid; width: 0px; height: 0.941em;\"></span></span></nobr><span class=\"MJX_Assistive_MathML\" role=\"presentation\"><math xmlns=\"http://www.w3.org/1998/Math/MathML\"><mi>l</mi></math></span></span><script type=\"math/tex\" id=\"MathJax-Element-23\">l</script>. When these activations are used in backward propagation, this leads to the exploding gradient problem. That is, the gradients of the cost with the respect to the parameters are too big. This leads the cost to oscillate around its minimum value.</li>\n</ul>",
    "contentMarkdown": "*   Consider the case where every weight is initialized slightly larger than the identity matrix.\n\nW\\[1\\]\\=W\\[2\\]\\=⋯\\=W\\[L−1\\]\\=\\[1.5001.5\\]W\\[1\\]\\=W\\[2\\]\\=⋯\\=W\\[L−1\\]\\=\\[1.5001.5\\]\n\n*   This simplifies to ŷ \\=W\\[L\\]1.5L−1xy^\\=W\\[L\\]1.5L−1x\\\\hat{y} = W^{\\[L\\]}1.5^{L-1}x, and the values of a\\[l\\]a\\[l\\]a^{\\[l\\]} increase exponentially with lll. When these activations are used in backward propagation, this leads to the exploding gradient problem. That is, the gradients of the cost with the respect to the parameters are too big. This leads the cost to oscillate around its minimum value.",
    "contentLength": 18975,
    "wordCount": 74,
    "hasCode": false,
    "hasMath": true,
    "hasImages": false,
    "url": "https://aman.ai/primers/ai/xavier-init/#case-1:-a-too-large-initialization-leads-to-exploding-gradients"
  },
  {
    "id": "ai-xavier-init-case-2-a-too-small-initialization-leads-to-vanishi-2",
    "articleSlug": "xavier-init",
    "articleTitle": "Xavier Initialization",
    "category": "Data/Training",
    "chapter": "The Problem of Exploding or Vanishing Gradients",
    "title": "Case 2: a Too-small Initialization Leads to Vanishing Gradients",
    "order": 2,
    "orderInChapter": 2,
    "contentHtml": "<ul>\n  <li>Similarly, consider the case where every weight is initialized slightly smaller than the identity matrix.</li>\n</ul>\n<div class=\"MathJax_Display\" style=\"text-align: center;\"><span class=\"MathJax\" id=\"MathJax-Element-24-Frame\" tabindex=\"0\" data-mathml=\"<math xmlns=&quot;http://www.w3.org/1998/Math/MathML&quot; display=&quot;block&quot;><msup><mi>W</mi><mrow class=&quot;MJX-TeXAtom-ORD&quot;><mo stretchy=&quot;false&quot;>[</mo><mn>1</mn><mo stretchy=&quot;false&quot;>]</mo></mrow></msup><mo>=</mo><msup><mi>W</mi><mrow class=&quot;MJX-TeXAtom-ORD&quot;><mo stretchy=&quot;false&quot;>[</mo><mn>2</mn><mo stretchy=&quot;false&quot;>]</mo></mrow></msup><mo>=</mo><mo>&amp;#x22EF;</mo><mo>=</mo><msup><mi>W</mi><mrow class=&quot;MJX-TeXAtom-ORD&quot;><mo stretchy=&quot;false&quot;>[</mo><mi>L</mi><mo>&amp;#x2212;</mo><mn>1</mn><mo stretchy=&quot;false&quot;>]</mo></mrow></msup><mo>=</mo><mrow><mo>[</mo><mtable rowspacing=&quot;4pt&quot; columnspacing=&quot;1em&quot;><mtr><mtd><mn>0.5</mn></mtd><mtd><mn>0</mn></mtd></mtr><mtr><mtd><mn>0</mn></mtd><mtd><mn>0.5</mn></mtd></mtr></mtable><mo>]</mo></mrow></math>\" role=\"presentation\" style=\"text-align: center; position: relative;\"><nobr aria-hidden=\"true\"><span class=\"math\" id=\"MathJax-Span-321\" style=\"width: 20.784em; display: inline-block;\"><span style=\"display: inline-block; position: relative; width: 17.294em; height: 0px; font-size: 120%;\"><span style=\"position: absolute; clip: rect(2.503em, 1017.09em, 5.263em, -999.997em); top: -4.112em; left: 0em;\"><span class=\"mrow\" id=\"MathJax-Span-322\"><span class=\"msubsup\" id=\"MathJax-Span-323\"><span style=\"display: inline-block; position: relative; width: 1.878em; height: 0px;\"><span style=\"position: absolute; clip: rect(3.18em, 1000.89em, 4.169em, -999.997em); top: -4.008em; left: 0em;\"><span class=\"mi\" id=\"MathJax-Span-324\" style=\"font-family: STIXGeneral-Italic;\">W<span style=\"display: inline-block; overflow: hidden; height: 1px; width: 0.055em;\"></span></span><span style=\"display: inline-block; width: 0px; height: 4.013em;\"></span></span><span style=\"position: absolute; top: -4.424em; left: 0.992em;\"><span class=\"texatom\" id=\"MathJax-Span-325\"><span class=\"mrow\" id=\"MathJax-Span-326\"><span class=\"mo\" id=\"MathJax-Span-327\" style=\"font-size: 70.7%; font-family: STIXGeneral-Regular;\">[</span><span class=\"mn\" id=\"MathJax-Span-328\" style=\"font-size: 70.7%; font-family: STIXGeneral-Regular;\">1</span><span class=\"mo\" id=\"MathJax-Span-329\" style=\"font-size: 70.7%; font-family: STIXGeneral-Regular;\">]</span></span></span><span style=\"display: inline-block; width: 0px; height: 4.013em;\"></span></span></span></span><span class=\"mo\" id=\"MathJax-Span-330\" style=\"font-family: STIXGeneral-Regular; padding-left: 0.315em;\">=</span><span class=\"msubsup\" id=\"MathJax-Span-331\" style=\"padding-left: 0.315em;\"><span style=\"display: inline-block; position: relative; width: 1.878em; height: 0px;\"><span style=\"position: absolute; clip: rect(3.18em, 1000.89em, 4.169em, -999.997em); top: -4.008em; left: 0em;\"><span class=\"mi\" id=\"MathJax-Span-332\" style=\"font-family: STIXGeneral-Italic;\">W<span style=\"display: inline-block; overflow: hidden; height: 1px; width: 0.055em;\"></span></span><span style=\"display: inline-block; width: 0px; height: 4.013em;\"></span></span><span style=\"position: absolute; top: -4.424em; left: 0.992em;\"><span class=\"texatom\" id=\"MathJax-Span-333\"><span class=\"mrow\" id=\"MathJax-Span-334\"><span class=\"mo\" id=\"MathJax-Span-335\" style=\"font-size: 70.7%; font-family: STIXGeneral-Regular;\">[</span><span class=\"mn\" id=\"MathJax-Span-336\" style=\"font-size: 70.7%; font-family: STIXGeneral-Regular;\">2</span><span class=\"mo\" id=\"MathJax-Span-337\" style=\"font-size: 70.7%; font-family: STIXGeneral-Regular;\">]</span></span></span><span style=\"display: inline-block; width: 0px; height: 4.013em;\"></span></span></span></span><span class=\"mo\" id=\"MathJax-Span-338\" style=\"font-family: STIXGeneral-Regular; padding-left: 0.315em;\">=</span><span class=\"mo\" id=\"MathJax-Span-339\" style=\"font-family: STIXGeneral-Regular; padding-left: 0.315em;\">⋯</span><span class=\"mo\" id=\"MathJax-Span-340\" style=\"font-family: STIXGeneral-Regular; padding-left: 0.315em;\">=</span><span class=\"msubsup\" id=\"MathJax-Span-341\" style=\"padding-left: 0.315em;\"><span style=\"display: inline-block; position: relative; width: 2.763em; height: 0px;\"><span style=\"position: absolute; clip: rect(3.18em, 1000.89em, 4.169em, -999.997em); top: -4.008em; left: 0em;\"><span class=\"mi\" id=\"MathJax-Span-342\" style=\"font-family: STIXGeneral-Italic;\">W<span style=\"display: inline-block; overflow: hidden; height: 1px; width: 0.055em;\"></span></span><span style=\"display: inline-block; width: 0px; height: 4.013em;\"></span></span><span style=\"position: absolute; top: -4.424em; left: 0.992em;\"><span class=\"texatom\" id=\"MathJax-Span-343\"><span class=\"mrow\" id=\"MathJax-Span-344\"><span class=\"mo\" id=\"MathJax-Span-345\" style=\"font-size: 70.7%; font-family: STIXGeneral-Regular;\">[</span><span class=\"mi\" id=\"MathJax-Span-346\" style=\"font-size: 70.7%; font-family: STIXGeneral-Italic;\">L<span style=\"display: inline-block; overflow: hidden; height: 1px; width: 0.003em;\"></span></span><span class=\"mo\" id=\"MathJax-Span-347\" style=\"font-size: 70.7%; font-family: STIXGeneral-Regular;\">−</span><span class=\"mn\" id=\"MathJax-Span-348\" style=\"font-size: 70.7%; font-family: STIXGeneral-Regular;\">1</span><span class=\"mo\" id=\"MathJax-Span-349\" style=\"font-size: 70.7%; font-family: STIXGeneral-Regular;\">]</span></span></span><span style=\"display: inline-block; width: 0px; height: 4.013em;\"></span></span></span></span><span class=\"mo\" id=\"MathJax-Span-350\" style=\"font-family: STIXGeneral-Regular; padding-left: 0.315em;\">=</span><span class=\"mrow\" id=\"MathJax-Span-351\" style=\"padding-left: 0.315em;\"><span class=\"mo\" id=\"MathJax-Span-352\" style=\"vertical-align: -0.57em;\"><span style=\"font-family: STIXSizeThreeSym;\">[</span></span><span class=\"mtable\" id=\"MathJax-Span-353\" style=\"padding-right: 0.159em; padding-left: 0.159em;\"><span style=\"display: inline-block; position: relative; width: 3.648em; height: 0px;\"><span style=\"position: absolute; clip: rect(2.503em, 1001.2em, 4.951em, -999.997em); top: -4.008em; left: 0em;\"><span style=\"display: inline-block; position: relative; width: 1.253em; height: 0px;\"><span style=\"position: absolute; clip: rect(3.18em, 1001.2em, 4.169em, -999.997em); top: -4.685em; left: 50%; margin-left: -0.622em;\"><span class=\"mtd\" id=\"MathJax-Span-354\"><span class=\"mrow\" id=\"MathJax-Span-355\"><span class=\"mn\" id=\"MathJax-Span-356\" style=\"font-family: STIXGeneral-Regular;\">0.5</span></span></span><span style=\"display: inline-block; width: 0px; height: 4.013em;\"></span></span><span style=\"position: absolute; clip: rect(3.18em, 1000.47em, 4.169em, -999.997em); top: -3.227em; left: 50%; margin-left: -0.258em;\"><span class=\"mtd\" id=\"MathJax-Span-360\"><span class=\"mrow\" id=\"MathJax-Span-361\"><span class=\"mn\" id=\"MathJax-Span-362\" style=\"font-family: STIXGeneral-Regular;\">0</span></span></span><span style=\"display: inline-block; width: 0px; height: 4.013em;\"></span></span></span><span style=\"display: inline-block; width: 0px; height: 4.013em;\"></span></span><span style=\"position: absolute; clip: rect(2.503em, 1001.2em, 4.951em, -999.997em); top: -4.008em; left: 2.398em;\"><span style=\"display: inline-block; position: relative; width: 1.253em; height: 0px;\"><span style=\"position: absolute; clip: rect(3.18em, 1000.47em, 4.169em, -999.997em); top: -4.685em; left: 50%; margin-left: -0.258em;\"><span class=\"mtd\" id=\"MathJax-Span-357\"><span class=\"mrow\" id=\"MathJax-Span-358\"><span class=\"mn\" id=\"MathJax-Span-359\" style=\"font-family: STIXGeneral-Regular;\">0</span></span></span><span style=\"display: inline-block; width: 0px; height: 4.013em;\"></span></span><span style=\"position: absolute; clip: rect(3.18em, 1001.2em, 4.169em, -999.997em); top: -3.227em; left: 50%; margin-left: -0.622em;\"><span class=\"mtd\" id=\"MathJax-Span-363\"><span class=\"mrow\" id=\"MathJax-Span-364\"><span class=\"mn\" id=\"MathJax-Span-365\" style=\"font-family: STIXGeneral-Regular;\">0.5</span></span></span><span style=\"display: inline-block; width: 0px; height: 4.013em;\"></span></span></span><span style=\"display: inline-block; width: 0px; height: 4.013em;\"></span></span></span></span><span class=\"mo\" id=\"MathJax-Span-366\" style=\"vertical-align: -0.57em;\"><span style=\"font-family: STIXSizeThreeSym;\">]</span></span></span></span><span style=\"display: inline-block; width: 0px; height: 4.117em;\"></span></span></span><span style=\"display: inline-block; overflow: hidden; vertical-align: -1.247em; border-left: 0px solid; width: 0px; height: 3.066em;\"></span></span></nobr><span class=\"MJX_Assistive_MathML MJX_Assistive_MathML_Block\" role=\"presentation\"><math xmlns=\"http://www.w3.org/1998/Math/MathML\" display=\"block\"><msup><mi>W</mi><mrow class=\"MJX-TeXAtom-ORD\"><mo stretchy=\"false\">[</mo><mn>1</mn><mo stretchy=\"false\">]</mo></mrow></msup><mo>=</mo><msup><mi>W</mi><mrow class=\"MJX-TeXAtom-ORD\"><mo stretchy=\"false\">[</mo><mn>2</mn><mo stretchy=\"false\">]</mo></mrow></msup><mo>=</mo><mo>⋯</mo><mo>=</mo><msup><mi>W</mi><mrow class=\"MJX-TeXAtom-ORD\"><mo stretchy=\"false\">[</mo><mi>L</mi><mo>−</mo><mn>1</mn><mo stretchy=\"false\">]</mo></mrow></msup><mo>=</mo><mrow><mo>[</mo><mtable rowspacing=\"4pt\" columnspacing=\"1em\"><mtr><mtd><mn>0.5</mn></mtd><mtd><mn>0</mn></mtd></mtr><mtr><mtd><mn>0</mn></mtd><mtd><mn>0.5</mn></mtd></mtr></mtable><mo>]</mo></mrow></math></span></span></div>\n<ul>\n  <li>This simplifies to <span class=\"MathJax_Preview\" style=\"color: inherit; display: none;\"></span><span class=\"MathJax\" id=\"MathJax-Element-25-Frame\" tabindex=\"0\" data-mathml=\"<math xmlns=&quot;http://www.w3.org/1998/Math/MathML&quot;><mrow class=&quot;MJX-TeXAtom-ORD&quot;><mover><mi>y</mi><mo stretchy=&quot;false&quot;>&amp;#x005E;</mo></mover></mrow><mo>=</mo><msup><mi>W</mi><mrow class=&quot;MJX-TeXAtom-ORD&quot;><mo stretchy=&quot;false&quot;>[</mo><mi>L</mi><mo stretchy=&quot;false&quot;>]</mo></mrow></msup><msup><mn>0.5</mn><mrow class=&quot;MJX-TeXAtom-ORD&quot;><mi>L</mi><mo>&amp;#x2212;</mo><mn>1</mn></mrow></msup><mi>x</mi></math>\" role=\"presentation\" style=\"position: relative;\"><nobr aria-hidden=\"true\"><span class=\"math\" id=\"MathJax-Span-367\" style=\"width: 8.023em; display: inline-block;\"><span style=\"display: inline-block; position: relative; width: 6.669em; height: 0px; font-size: 120%;\"><span style=\"position: absolute; clip: rect(1.148em, 1006.67em, 2.555em, -999.997em); top: -2.185em; left: 0em;\"><span class=\"mrow\" id=\"MathJax-Span-368\"><span class=\"texatom\" id=\"MathJax-Span-369\"><span class=\"mrow\" id=\"MathJax-Span-370\"><span class=\"munderover\" id=\"MathJax-Span-371\"><span style=\"display: inline-block; position: relative; width: 0.471em; height: 0px;\"><span style=\"position: absolute; clip: rect(3.44em, 1000.42em, 4.378em, -999.997em); top: -4.008em; left: 0em;\"><span class=\"mi\" id=\"MathJax-Span-372\" style=\"font-family: STIXGeneral-Italic;\">y</span><span style=\"display: inline-block; width: 0px; height: 4.013em;\"></span></span><span style=\"position: absolute; top: -4.06em; left: 0.055em;\"><span style=\"height: 0em; vertical-align: 0em; width: 0.367em; display: inline-block; overflow: hidden;\"></span><span class=\"mo\" id=\"MathJax-Span-373\" style=\"font-family: STIXGeneral-Regular;\">̂&nbsp;<span style=\"height: 0em; vertical-align: 0em; margin-left: -0.258em;\"></span></span><span style=\"display: inline-block; overflow: hidden; height: 1px; width: 0em;\"></span><span style=\"display: inline-block; width: 0px; height: 4.013em;\"></span></span></span></span></span></span><span class=\"mo\" id=\"MathJax-Span-374\" style=\"font-family: STIXGeneral-Regular; padding-left: 0.315em;\">=</span><span class=\"msubsup\" id=\"MathJax-Span-375\" style=\"padding-left: 0.315em;\"><span style=\"display: inline-block; position: relative; width: 1.93em; height: 0px;\"><span style=\"position: absolute; clip: rect(3.18em, 1000.89em, 4.169em, -999.997em); top: -4.008em; left: 0em;\"><span class=\"mi\" id=\"MathJax-Span-376\" style=\"font-family: STIXGeneral-Italic;\">W<span style=\"display: inline-block; overflow: hidden; height: 1px; width: 0.055em;\"></span></span><span style=\"display: inline-block; width: 0px; height: 4.013em;\"></span></span><span style=\"position: absolute; top: -4.372em; left: 0.992em;\"><span class=\"texatom\" id=\"MathJax-Span-377\"><span class=\"mrow\" id=\"MathJax-Span-378\"><span class=\"mo\" id=\"MathJax-Span-379\" style=\"font-size: 70.7%; font-family: STIXGeneral-Regular;\">[</span><span class=\"mi\" id=\"MathJax-Span-380\" style=\"font-size: 70.7%; font-family: STIXGeneral-Italic;\">L<span style=\"display: inline-block; overflow: hidden; height: 1px; width: 0.003em;\"></span></span><span class=\"mo\" id=\"MathJax-Span-381\" style=\"font-size: 70.7%; font-family: STIXGeneral-Regular;\">]</span></span></span><span style=\"display: inline-block; width: 0px; height: 4.013em;\"></span></span></span></span><span class=\"msubsup\" id=\"MathJax-Span-382\"><span style=\"display: inline-block; position: relative; width: 2.555em; height: 0px;\"><span style=\"position: absolute; clip: rect(3.18em, 1001.2em, 4.169em, -999.997em); top: -4.008em; left: 0em;\"><span class=\"mn\" id=\"MathJax-Span-383\" style=\"font-family: STIXGeneral-Regular;\">0.5</span><span style=\"display: inline-block; width: 0px; height: 4.013em;\"></span></span><span style=\"position: absolute; top: -4.424em; left: 1.253em;\"><span class=\"texatom\" id=\"MathJax-Span-384\"><span class=\"mrow\" id=\"MathJax-Span-385\"><span class=\"mi\" id=\"MathJax-Span-386\" style=\"font-size: 70.7%; font-family: STIXGeneral-Italic;\">L<span style=\"display: inline-block; overflow: hidden; height: 1px; width: 0.003em;\"></span></span><span class=\"mo\" id=\"MathJax-Span-387\" style=\"font-size: 70.7%; font-family: STIXGeneral-Regular;\">−</span><span class=\"mn\" id=\"MathJax-Span-388\" style=\"font-size: 70.7%; font-family: STIXGeneral-Regular;\">1</span></span></span><span style=\"display: inline-block; width: 0px; height: 4.013em;\"></span></span></span></span><span class=\"mi\" id=\"MathJax-Span-389\" style=\"font-family: STIXGeneral-Italic;\">x<span style=\"display: inline-block; overflow: hidden; height: 1px; width: 0.003em;\"></span></span></span><span style=\"display: inline-block; width: 0px; height: 2.19em;\"></span></span></span><span style=\"display: inline-block; overflow: hidden; vertical-align: -0.309em; border-left: 0px solid; width: 0px; height: 1.441em;\"></span></span></nobr><span class=\"MJX_Assistive_MathML\" role=\"presentation\"><math xmlns=\"http://www.w3.org/1998/Math/MathML\"><mrow class=\"MJX-TeXAtom-ORD\"><mover><mi>y</mi><mo stretchy=\"false\">^</mo></mover></mrow><mo>=</mo><msup><mi>W</mi><mrow class=\"MJX-TeXAtom-ORD\"><mo stretchy=\"false\">[</mo><mi>L</mi><mo stretchy=\"false\">]</mo></mrow></msup><msup><mn>0.5</mn><mrow class=\"MJX-TeXAtom-ORD\"><mi>L</mi><mo>−</mo><mn>1</mn></mrow></msup><mi>x</mi></math></span></span><script type=\"math/tex\" id=\"MathJax-Element-25\">\\hat{y} = W^{[L]}0.5^{L-1}x</script>, and the values of the activation <span class=\"MathJax_Preview\" style=\"color: inherit; display: none;\"></span><span class=\"MathJax\" id=\"MathJax-Element-26-Frame\" tabindex=\"0\" data-mathml=\"<math xmlns=&quot;http://www.w3.org/1998/Math/MathML&quot;><msup><mi>a</mi><mrow class=&quot;MJX-TeXAtom-ORD&quot;><mo stretchy=&quot;false&quot;>[</mo><mi>l</mi><mo stretchy=&quot;false&quot;>]</mo></mrow></msup></math>\" role=\"presentation\" style=\"position: relative;\"><nobr aria-hidden=\"true\"><span class=\"math\" id=\"MathJax-Span-390\" style=\"width: 1.513em; display: inline-block;\"><span style=\"display: inline-block; position: relative; width: 1.253em; height: 0px; font-size: 120%;\"><span style=\"position: absolute; clip: rect(1.148em, 1001.25em, 2.294em, -999.997em); top: -2.133em; left: 0em;\"><span class=\"mrow\" id=\"MathJax-Span-391\"><span class=\"msubsup\" id=\"MathJax-Span-392\"><span style=\"display: inline-block; position: relative; width: 1.253em; height: 0px;\"><span style=\"position: absolute; clip: rect(3.44em, 1000.47em, 4.169em, -999.997em); top: -4.008em; left: 0em;\"><span class=\"mi\" id=\"MathJax-Span-393\" style=\"font-family: STIXGeneral-Italic;\">a</span><span style=\"display: inline-block; width: 0px; height: 4.013em;\"></span></span><span style=\"position: absolute; top: -4.372em; left: 0.523em;\"><span class=\"texatom\" id=\"MathJax-Span-394\"><span class=\"mrow\" id=\"MathJax-Span-395\"><span class=\"mo\" id=\"MathJax-Span-396\" style=\"font-size: 70.7%; font-family: STIXGeneral-Regular;\">[</span><span class=\"mi\" id=\"MathJax-Span-397\" style=\"font-size: 70.7%; font-family: STIXGeneral-Italic;\">l<span style=\"display: inline-block; overflow: hidden; height: 1px; width: 0.003em;\"></span></span><span class=\"mo\" id=\"MathJax-Span-398\" style=\"font-size: 70.7%; font-family: STIXGeneral-Regular;\">]</span></span></span><span style=\"display: inline-block; width: 0px; height: 4.013em;\"></span></span></span></span></span><span style=\"display: inline-block; width: 0px; height: 2.138em;\"></span></span></span><span style=\"display: inline-block; overflow: hidden; vertical-align: -0.059em; border-left: 0px solid; width: 0px; height: 1.128em;\"></span></span></nobr><span class=\"MJX_Assistive_MathML\" role=\"presentation\"><math xmlns=\"http://www.w3.org/1998/Math/MathML\"><msup><mi>a</mi><mrow class=\"MJX-TeXAtom-ORD\"><mo stretchy=\"false\">[</mo><mi>l</mi><mo stretchy=\"false\">]</mo></mrow></msup></math></span></span><script type=\"math/tex\" id=\"MathJax-Element-26\">a^{[l]}</script> decrease exponentially with <span class=\"MathJax_Preview\" style=\"color: inherit; display: none;\"></span><span class=\"MathJax\" id=\"MathJax-Element-27-Frame\" tabindex=\"0\" data-mathml=\"<math xmlns=&quot;http://www.w3.org/1998/Math/MathML&quot;><mi>l</mi></math>\" role=\"presentation\" style=\"position: relative;\"><nobr aria-hidden=\"true\"><span class=\"math\" id=\"MathJax-Span-399\" style=\"width: 0.315em; display: inline-block;\"><span style=\"display: inline-block; position: relative; width: 0.263em; height: 0px; font-size: 120%;\"><span style=\"position: absolute; clip: rect(1.357em, 1000.26em, 2.346em, -999.997em); top: -2.185em; left: 0em;\"><span class=\"mrow\" id=\"MathJax-Span-400\"><span class=\"mi\" id=\"MathJax-Span-401\" style=\"font-family: STIXGeneral-Italic;\">l<span style=\"display: inline-block; overflow: hidden; height: 1px; width: 0.003em;\"></span></span></span><span style=\"display: inline-block; width: 0px; height: 2.19em;\"></span></span></span><span style=\"display: inline-block; overflow: hidden; vertical-align: -0.059em; border-left: 0px solid; width: 0px; height: 0.941em;\"></span></span></nobr><span class=\"MJX_Assistive_MathML\" role=\"presentation\"><math xmlns=\"http://www.w3.org/1998/Math/MathML\"><mi>l</mi></math></span></span><script type=\"math/tex\" id=\"MathJax-Element-27\">l</script>. When these activations are used in backward propagation, this leads to the vanishing gradient problem. The gradients of the cost with respect to the parameters are too small, leading to convergence of the cost before it has reached the minimum value.</li>\n  <li>All in all, initializing weights with inappropriate values will lead to divergence or a slow-down in the training of your neural network. Although we illustrated the exploding/vanishing gradient problem with simple symmetrical weight matrices, the observation generalizes to any initialization values that are too small or too large.</li>\n</ul>",
    "contentMarkdown": "*   Similarly, consider the case where every weight is initialized slightly smaller than the identity matrix.\n\nW\\[1\\]\\=W\\[2\\]\\=⋯\\=W\\[L−1\\]\\=\\[0.5000.5\\]W\\[1\\]\\=W\\[2\\]\\=⋯\\=W\\[L−1\\]\\=\\[0.5000.5\\]\n\n*   This simplifies to ŷ \\=W\\[L\\]0.5L−1xy^\\=W\\[L\\]0.5L−1x\\\\hat{y} = W^{\\[L\\]}0.5^{L-1}x, and the values of the activation a\\[l\\]a\\[l\\]a^{\\[l\\]} decrease exponentially with lll. When these activations are used in backward propagation, this leads to the vanishing gradient problem. The gradients of the cost with respect to the parameters are too small, leading to convergence of the cost before it has reached the minimum value.\n*   All in all, initializing weights with inappropriate values will lead to divergence or a slow-down in the training of your neural network. Although we illustrated the exploding/vanishing gradient problem with simple symmetrical weight matrices, the observation generalizes to any initialization values that are too small or too large.",
    "contentLength": 19353,
    "wordCount": 126,
    "hasCode": false,
    "hasMath": true,
    "hasImages": false,
    "url": "https://aman.ai/primers/ai/xavier-init/#case-2:-a-too-small-initialization-leads-to-vanishing-gradients"
  }
]