[
  {
    "id": "prob_for_naive_bayes_004",
    "subject": "probability",
    "type": "formula",
    "chapter": "ml_probability",
    "topic": "naive_bayes",
    "title": "Naive Bayes Classifier",
    "contentHtml": "<p>The Naive Bayes classifier is a popular probabilistic approach in machine learning that assumes independence between features.</p>",
    "formula": "{",
    "latex": "\\\\[P(y \\mid x) = \\\\frac{P(x \\mid y) P(y)}{P(x)}\\\\]\",",
    "name": "Bayes' theorem\" },",
    "workedExample": "{",
    "problemHtml": "<p>Suppose we have a dataset of images with labels (0 or 1), and we want to classify new images.</p>",
    "steps": "[ {\"stepNumber\": 1, \"description\": \"Define the prior probability P(y)\", \"mathHtml\": \"\\\\[P(y) = \\\\frac{1}{2}\\\\]\", \"explanation\": \"This is our initial belief about the class distribution\"}, {\"stepNumber\": 2, \"description\": \"Calculate the likelihood P(x \\mid y)\", \"mathHtml\": \"\\\\[P(x \\mid y) = \\\\prod_{i} P(x_i \\mid y)\\\\]\", \"explanation\": \"We assume independence between features\"} ],",
    "finalAnswer": "Classify new images based on their feature values\" },",
    "intuition": "The Naive Bayes classifier is a simple yet effective approach that works well when the features are independent.",
    "difficulty": 3,
    "mlRelevance": "core",
    "prerequisites": [],
    "relatedCards": [],
    "nextCards": [],
    "generatedAt": "2025-12-27T02:54:17.668Z",
    "generatedBy": "llama3:latest",
    "reviewed": false,
    "version": 1
  },
  {
    "id": "prob_for_naive_bayes_005",
    "subject": "probability",
    "type": "formula",
    "chapter": "ml_probability",
    "topic": "naive_bayes",
    "title": "Naive Bayes Classifier Formula",
    "contentHtml": "<p>The Naive Bayes classifier is a probabilistic machine learning model that assumes independence between features.</p><p>This formula is used for training and prediction in the Naive Bayes algorithm.</p>",
    "formula": "{",
    "latex": "\\[P(y | x) = \\frac{1}{P(x)} \\prod_{i=1}^n P(x_i | y)\\]\",",
    "name": "Bayes' Theorem",
    "variants": "[] },",
    "workedExample": "{",
    "problemHtml": "<p>Suppose we have a dataset of images labeled as either 'dog' or 'cat'. We want to train a Naive Bayes classifier to predict the class label given an image.</p>",
    "steps": "[ {\"stepNumber\": 1, \"description\": \"Calculate the prior probability of each class\", \"mathHtml\": \"\\\\[P(y) = \\\\frac{1}{2}\\]\", \"explanation\": \"The prior probability is the probability of the class before considering any features.\"} ],",
    "finalAnswer": "The trained classifier\" },",
    "intuition": "This formula represents the probability of a class given an instance, which is used to make predictions in the Naive Bayes algorithm.",
    "difficulty": 3,
    "mlRelevance": "core",
    "prerequisites": [],
    "relatedCards": [],
    "nextCards": [],
    "generatedAt": "2025-12-27T02:54:37.647Z",
    "generatedBy": "llama3:latest",
    "reviewed": false,
    "version": 1
  },
  {
    "id": "prob_for_naive_bayes_006",
    "subject": "probability",
    "type": "formula",
    "chapter": "ml_probability",
    "topic": "naive_bayes",
    "title": "Naive Bayes Classifier",
    "contentHtml": "<p>The Naive Bayes classifier is a probabilistic machine learning algorithm that assumes independence between features.</p>",
    "formula": "{",
    "latex": "\\\\[ P(y \\mid x) = \\\\frac{P(x \\mid y) P(y)}{P(x)} \\\\]\",",
    "name": "Bayes' theorem\" },",
    "workedExample": "{",
    "problemHtml": "<p>Given a dataset of handwritten digits, train a Naive Bayes classifier to classify new images.</p>",
    "steps": "[ {\"stepNumber\": 1, \"description\": \"Calculate the prior probability of each class\", \"mathHtml\": \"\\\\[ P(y) = \\\\frac{\\\\text{\\# instances in class } y}{\\\\text{\\# total instances}} \\\\]\", \"explanation\": \"This represents our initial understanding of the classes.\"}, {\"stepNumber\": 2, \"description\": \"Calculate the likelihood of each feature given a class\", \"mathHtml\": \"\\\\[ P(x \\mid y) = \\\\frac{\\\\text{\\# instances in class } y \\\\text{ with feature } x}{P(y)} \\\\]\", \"explanation\": \"This represents how likely we are to see a certain feature given a class.\"} ],",
    "finalAnswer": "The trained classifier\" },",
    "intuition": "By assuming independence between features, the Naive Bayes classifier becomes computationally efficient and easy to interpret.",
    "realWorldApplications": [
      "Image classification",
      "Text classification"
    ],
    "difficulty": 3,
    "mlRelevance": "core",
    "prerequisites": [],
    "relatedCards": [],
    "nextCards": [],
    "generatedAt": "2025-12-27T02:54:59.622Z",
    "generatedBy": "llama3:latest",
    "reviewed": false,
    "version": 1
  },
  {
    "id": "prob_for_naive_bayes_007",
    "subject": "probability",
    "type": "formula",
    "chapter": "ml_probability",
    "topic": "naive_bayes",
    "title": "Naive Bayes Classifier Formula",
    "contentHtml": "<p>The Naive Bayes classifier is a popular probabilistic approach in machine learning.</p><p>It's based on the Bayes theorem and assumes independence between features.</p>",
    "formula": "{",
    "latex": "\\[P(y \\mid x) = \\frac{1}{P(x)} \\prod_{i=1}^n P(x_i \\mid y)\\]\",",
    "name": "Bayes' Theorem for Naive Bayes\" },",
    "workedExample": "{",
    "problemHtml": "<p>Suppose we have a dataset of images with labels (0 or 1) representing whether an image is of a cat or not.</p>",
    "steps": "[ {\"stepNumber\": 1, \"description\": \"Define the prior probability P(y=0) and P(y=1)\", \"mathHtml\": \"\\(P(y=0) = 0.5\\), \\(P(y=1) = 0.5\\)\", \"explanation\": \"We assume equal prior probabilities\"}, {\"stepNumber\": 2, \"description\": \"Calculate the likelihoods P(x_i \\mid y)\"\", \"mathHtml\": \"\\(P(x_1 \\mid y=0) = 0.7\\), \\(P(x_1 \\mid y=1) = 0.3\\)\", \"explanation\": \"These are conditional probabilities of features given class labels\"} ],",
    "finalAnswer": "The posterior probability P(y=0|x) is calculated using the formula\" },",
    "intuition": "The Naive Bayes classifier assumes independence between features, which simplifies the calculation. This assumption is often reasonable in many real-world scenarios.",
    "difficulty": 3,
    "mlRelevance": "core",
    "prerequisites": [],
    "relatedCards": [],
    "nextCards": [],
    "generatedAt": "2025-12-27T02:55:24.739Z",
    "generatedBy": "llama3:latest",
    "reviewed": false,
    "version": 1
  }
]