[
  {
    "id": "la_prb_vector_geometry_007",
    "subject": "linear_algebra",
    "type": "problem",
    "chapter": "vectors_foundations",
    "topic": "vector_geometry",
    "problem": "{",
    "statementHtml": "<p>Find the magnitude and direction of vector <strong>\\(\\mathbf{v}\\)</strong> in R².</p>\",",
    "hints": [
      "Think about the geometric interpretation of vectors as arrows.",
      "Recall that the magnitude is the length of the arrow, while the direction is its orientation."
    ],
    "solutionHtml": "<p>To find the magnitude, use the formula <strong>\\(\\|\\mathbf{v}\\| = \\sqrt{x^2 + y^2}\\)</strong>, where <strong>\\(x\\)</strong> and <strong>\\(y\\)</strong> are the components of <strong>\\(\\mathbf{v}\\)</strong>.</p><p>To find the direction, consider that vectors in R² can be represented as arrows with initial point at the origin. The direction is then given by the angle between the arrow and the positive x-axis.</p>\",",
    "answerShort": "<strong>Answer:</strong> Magnitude: <latex>\\(\\sqrt{x^2 + y^2}\\)</latex>, Direction: Angle from positive x-axis\" },",
    "difficulty": 1,
    "mlRelevance": "core",
    "prerequisites": [],
    "relatedCards": [],
    "nextCards": [],
    "generatedAt": "2025-12-26T09:14:25.313Z",
    "generatedBy": "llama3:latest",
    "reviewed": false,
    "version": 1
  },
  {
    "id": "la_prb_vector_geometry_008",
    "subject": "linear_algebra",
    "type": "problem",
    "chapter": "vectors_foundations",
    "topic": "vector_geometry",
    "problem": "{",
    "statementHtml": "<p>Find the magnitude of vector <math>\\mathbf{v} = (3, -4)</math>.</p>\",",
    "hints": "[ \"Think about the Pythagorean theorem.\", \"Use the formula for the magnitude of a vector: <math>\\left\\lVert \\mathbf{v} \\right\\rVert = \\sqrt{\\mathbf{v} \\cdot \\mathbf{v}}</math>.\", \"You can also use the geometric interpretation to visualize the problem.\" ],",
    "solutionHtml": "<p>To find the magnitude, we need to calculate the dot product of <math>\\mathbf{v}</math> with itself:</p><p><math>\\left\\lVert \\mathbf{v} \\right\\rVert = \\sqrt{(3)^2 + (-4)^2} = \\sqrt{9+16} = \\sqrt{25} = 5</math>.</p>\",",
    "answerShort": "The magnitude is 5.\" },",
    "difficulty": 1,
    "mlRelevance": "core",
    "prerequisites": [],
    "relatedCards": [],
    "nextCards": [],
    "generatedAt": "2025-12-26T09:14:41.039Z",
    "generatedBy": "llama3:latest",
    "reviewed": false,
    "version": 1
  },
  {
    "id": "la_prb_vector_geometry_009",
    "subject": "linear_algebra",
    "type": "problem",
    "chapter": "vectors_foundations",
    "topic": "vector_geometry",
    "problem": "{",
    "statementHtml": "Find the magnitude of vector <strong>\\(\\mathbf{v} = (3, -4)\\)</strong> in R².\",",
    "hints": "[ \"Think about the Pythagorean theorem for right triangles.\", \"Use the formula for the magnitude of a 2D vector: \\(\\|\\mathbf{v}\\| = \\sqrt{x^2 + y^2}\\).\", \"Plug in the values and simplify.\" ],",
    "solutionHtml": "<p>To find the magnitude, we can use the formula:</p><p>\\(\\|\\mathbf{v}\\| = \\sqrt{(3)^2 + (-4)^2} = \\sqrt{9 + 16} = \\sqrt{25} = \\boxed{5}\\)</p>\",",
    "answerShort": "The magnitude is 5.\" },",
    "difficulty": 1,
    "mlRelevance": "core",
    "prerequisites": [],
    "relatedCards": [],
    "nextCards": [],
    "generatedAt": "2025-12-26T09:14:55.660Z",
    "generatedBy": "llama3:latest",
    "reviewed": false,
    "version": 1
  }
]